<?xml version="1.0" encoding="utf-8"?>
<key id="fd36394a-ae6b-4ad2-927a-e32226321c10" version="1">
  <creationDate>2025-10-09T03:07:12.58252Z</creationDate>
  <activationDate>2025-10-09T03:07:12.577301Z</activationDate>
  <expirationDate>2026-01-07T03:07:12.577301Z</expirationDate>
  <descriptor deserializerType="Microsoft.AspNetCore.DataProtection.AuthenticatedEncryption.ConfigurationModel.AuthenticatedEncryptorDescriptorDeserializer, Microsoft.AspNetCore.DataProtection, Version=8.0.0.0, Culture=neutral, PublicKeyToken=adb9793829ddae60">
    <descriptor>
      <encryption algorithm="AES_256_CBC" />
      <validation algorithm="HMACSHA256" />
      <masterKey p4:requiresEncryption="true" xmlns:p4="http://schemas.asp.net/2015/03/dataProtection">
        <!-- Warning: the key below is in an unencrypted form. -->
        <value>JXoeLxGYeacjA4lHMgNozAPv345ntkEHUAAaD8VEs+E/io/pJM01Tr2F9LEvvUNBKd9uJlBg+MDBttRYJTWRRw==</value>
      </masterKey>
    </descriptor>
  </descriptor>
</key>